datagem/__init__.py
datagem/pdf.py
datagem-0.1.1.dist-info/licenses/LICENSE
datagem-0.1.1.dist-info/METADATA
datagem-0.1.1.dist-info/WHEEL
datagem-0.1.1.dist-info/top_level.txt
datagem-0.1.1.dist-info/RECORD
