Metadata-Version: 2.4
Name: datagem
Version: 0.1.1
Summary: Um pacote para extrair informações de PDFs usando a API do Google Gemini.
Author-email: Gilberto Pereira Sassi <sassi.pereira.gilberto@gmail.com>
Project-URL: Homepage, https://github.com/obec-pesquisas/datagem
Project-URL: Bug Tracker, https://github.com/obec-pesquisas/datagem/issues
Classifier: Programming Language :: Python :: 3
Classifier: License :: OSI Approved :: MIT License
Classifier: Operating System :: OS Independent
Requires-Python: >=3.8
License-File: LICENSE
Requires-Dist: google-genai
Requires-Dist: pandas
Dynamic: license-file
